lissajou/__init__.py
lissajou/anim.py
lissajou/lissajou.py
lissajou-0.2.0.dist-info/METADATA
lissajou-0.2.0.dist-info/WHEEL
lissajou-0.2.0.dist-info/RECORD
