Metadata-Version: 2.1
Name: lissajou
Version: 0.2.0
Summary: A Python module for creating animations, including Lissajou curve simulations.
Home-page: https://hermann-web.github.io/blog/projects/introducing-lissajou-for-animated-plots/
License: MIT
Keywords: animation,matplotlib,simulation,Lissajou,parametric,visualization
Author: Hermann Agossou
Maintainer: Hermann Agossou
Maintainer-email: agossouhermann7@gmail.com
Requires-Python: >=3.8,<4.0
Classifier: Development Status :: 4 - Beta
Classifier: Intended Audience :: Developers
Classifier: License :: OSI Approved :: MIT License
Classifier: Programming Language :: Python :: 3
Classifier: Programming Language :: Python :: 3.8
Classifier: Programming Language :: Python :: 3.9
Classifier: Programming Language :: Python :: 3.10
Classifier: Programming Language :: Python :: 3.11
Classifier: Programming Language :: Python :: 3.12
Classifier: Topic :: Software Development :: Libraries :: Python Modules
Requires-Dist: matplotlib (>=3.4.0,<4.0.0)
Requires-Dist: numpy (>=1.23.0,<2.0.0)
Project-URL: Documentation, https://github.com/Hermann-web/lissajou/blob/main/docs/index.md
Project-URL: Repository, https://github.com/Hermann-web/lissajou
